{
  "NANY": {
    "forwarding_paths": "a2d2d1dd-433f-47b7-89f8-be3cd6b2086a",
    "status": "PENDING_CREATE",
    "description": "",
    "tenant_id": "058079ca392749bfa58831e0467a5439",
    "NANYD_id": "5263b036-8d11-410c-9417-6e0300456160",
    "mea_mapping": {
      "MEAD2": "af76238b-75db-4f70-9ad7-bd286bb0f88a",
      "MEAD1": "dcda3482-1e75-4b37-8bdd-77c018a59cd7"
    },
    "attributes": {
      "NANYD": {
        "imports": [
          "/opt/stack/apmec/apmec/tosca/lib/apmec_defs.yaml",
          "/opt/stack/apmec/apmec/tosca/lib/apmec_nfv_defs.yaml"
        ],
        "description": "Sample NFY template",
        "topology_template": {
          "node_templates": {
            "Forwarding_path1": {
              "type": "tosca.nodes.nfv.FP.Apmec",
              "description": "creates path (CP12->CP22)",
              "properties": {
                "policy": {
                  "type": "ACL",
                  "criteria": [
                    {
                      "network_src_port_id": "9ec6bef0-5da9-4b04-bdc7-c57bc26bcdea"
                    },
                    {
                      "ip_proto": 1
                    }
                  ]
                },
                "path": [
                  {
                    "capability": "CP12",
                    "forwarder": "MEAD1"
                  },
                  {
                    "capability": "CP22",
                    "forwarder": "MEAD2"
                  }
                ],
                "id": 51
              }
            }
          },
          "description": "Sample NFY template",
          "groups": {
            "NFY1": {
              "type": "tosca.groups.nfv.NFY",
              "description": "HTTP to Corporate Net",
              "members": [
                "Forwarding_path1"
              ],
              "properties": {
                "vendor": "apmec",
                "connection_point": [
                  "CP12",
                  "CP22"
                ],
                "version": 1,
                "constituent_meas": [
                  "MEAD1",
                  "MEAD2"
                ],
                "number_of_endpoints": 2,
                "dependent_virtual_link": [
                  "VL12",
                  "VL22"
                ]
              }
            }
          }
        },
        "tosca_definitions_version": "tosca_simple_profile_for_nfv_1_0_0"
      }
    },
    "id": "d86b2e7c-6e88-4d6e-ac1a-9a9ad56b48f5",
    "name": "NANY1"
  }
}